{"type":"FeatureCollection","features":[{"type":"Feature","properties":{"scalerank":10,"natscale":1,"labelrank":7,"featurecla":"Admin-1 capital","name":"Bregenz","namepar":null,"namealt":null,"diffascii":0,"nameascii":"Bregenz","adm0cap":0,"capalt":0,"capin":null,"worldcity":0,"megacity":0,"sov0name":"Austria","sov_a3":"AUT","adm0name":"Austria","adm0_a3":"AUT","adm1name":"Vorarlberg","iso_a2":"AT","note":null,"latitude":47.5166970658,"longitude":9.76670158807,"changed":4,"namediff":1,"pop_max":26928,"pop_min":26928,"pop_other":0,"rank_max":7,"rank_min":7,"geonameid":2781503,"meganame":null,"ls_name":null,"ls_match":0,"checkme":0,"min_zoom":8,"ne_id":1159121131,"continent":"Europe"},"geometry":{"type":"Point","coordinates":[9.766701588074284,47.51669706581856]}},{"type":"Feature","properties":{"scalerank":10,"natscale":1,"labelrank":7,"featurecla":"Admin-1 capital","name":"Eisenstadt","namepar":null,"namealt":null,"diffascii":0,"nameascii":"Eisenstadt","adm0cap":0,"capalt":0,"capin":null,"worldcity":0,"megacity":0,"sov0name":"Austria","sov_a3":"AUT","adm0name":"Austria","adm0_a3":"AUT","adm1name":"Burgenland","iso_a2":"AT","note":null,"latitude":47.8332990787,"longitude":16.5332974676,"changed":4,"namediff":1,"pop_max":13165,"pop_min":13165,"pop_other":0,"rank_max":6,"rank_min":6,"geonameid":2780190,"meganame":null,"ls_name":null,"ls_match":0,"checkme":0,"min_zoom":7,"ne_id":1159121147,"continent":"Europe"},"geometry":{"type":"Point","coordinates":[16.533297467606985,47.83329907874423]}},{"type":"Feature","properties":{"scalerank":8,"natscale":10,"labelrank":7,"featurecla":"Populated place","name":"Wiener Neustadt","namepar":null,"namealt":null,"diffascii":0,"nameascii":"Wiener Neustadt","adm0cap":0,"capalt":0,"capin":null,"worldcity":0,"megacity":0,"sov0name":"Austria","sov_a3":"AUT","adm0name":"Austria","adm0_a3":"AUT","adm1name":"Nieder\u00f6sterreich","iso_a2":"AT","note":null,"latitude":47.8159818716,"longitude":16.2499535712,"changed":40,"namediff":0,"pop_max":82762,"pop_min":38481,"pop_other":128401,"rank_max":8,"rank_min":7,"geonameid":2761353,"meganame":null,"ls_name":"Wiener","ls_match":1,"checkme":0,"min_zoom":6.1,"ne_id":1159132297,"continent":"Europe"},"geometry":{"type":"Point","coordinates":[16.249953571241463,47.81598187162706]}},{"type":"Feature","properties":{"scalerank":7,"natscale":20,"labelrank":7,"featurecla":"Admin-1 capital","name":"Graz","namepar":null,"namealt":null,"diffascii":0,"nameascii":"Graz","adm0cap":0,"capalt":0,"capin":null,"worldcity":0,"megacity":0,"sov0name":"Austria","sov_a3":"AUT","adm0name":"Austria","adm0_a3":"AUT","adm1name":"Steiermark","iso_a2":"AT","note":null,"latitude":47.0777581981,"longitude":15.4100048408,"changed":0,"namediff":0,"pop_max":263234,"pop_min":222326,"pop_other":248342,"rank_max":10,"rank_min":10,"geonameid":2778067,"meganame":null,"ls_name":"Graz","ls_match":1,"checkme":0,"min_zoom":6.1,"ne_id":1159145083,"continent":"Europe"},"geometry":{"type":"Point","coordinates":[15.410004840769432,47.077758198121444]}},{"type":"Feature","properties":{"scalerank":7,"natscale":20,"labelrank":7,"featurecla":"Admin-1 capital","name":"Klagenfurt","namepar":null,"namealt":null,"diffascii":0,"nameascii":"Klagenfurt","adm0cap":0,"capalt":0,"capin":null,"worldcity":0,"megacity":0,"sov0name":"Austria","sov_a3":"AUT","adm0name":"Austria","adm0_a3":"AUT","adm1name":"K\u00e4rnten","iso_a2":"AT","note":null,"latitude":46.6203442577,"longitude":14.310020303,"changed":0,"namediff":0,"pop_max":90610,"pop_min":86566,"pop_other":84897,"rank_max":8,"rank_min":8,"geonameid":2774326,"meganame":null,"ls_name":"Klagenfurt","ls_match":1,"checkme":0,"min_zoom":6.1,"ne_id":1159145087,"continent":"Europe"},"geometry":{"type":"Point","coordinates":[14.310020303004592,46.62034425768991]}},{"type":"Feature","properties":{"scalerank":7,"natscale":20,"labelrank":7,"featurecla":"Admin-1 capital","name":"Linz","namepar":null,"namealt":null,"diffascii":0,"nameascii":"Linz","adm0cap":0,"capalt":0,"capin":null,"worldcity":0,"megacity":0,"sov0name":"Austria","sov_a3":"AUT","adm0name":"Austria","adm0_a3":"AUT","adm1name":"Ober\u00f6sterreich","iso_a2":"AT","note":null,"latitude":48.3192328075,"longitude":14.2887812893,"changed":0,"namediff":0,"pop_max":349161,"pop_min":181162,"pop_other":257810,"rank_max":10,"rank_min":9,"geonameid":2772400,"meganame":null,"ls_name":"Linz","ls_match":1,"checkme":0,"min_zoom":6.1,"ne_id":1159145093,"continent":"Europe"},"geometry":{"type":"Point","coordinates":[14.28878128933269,48.31923280750141]}},{"type":"Feature","properties":{"scalerank":7,"natscale":20,"labelrank":7,"featurecla":"Admin-1 capital","name":"Salzburg","namepar":null,"namealt":null,"diffascii":0,"nameascii":"Salzburg","adm0cap":0,"capalt":0,"capin":null,"worldcity":0,"megacity":0,"sov0name":"Austria","sov_a3":"AUT","adm0name":"Austria","adm0_a3":"AUT","adm1name":"Salzburg","iso_a2":"AT","note":null,"latitude":47.8104783316,"longitude":13.040020303,"changed":0,"namediff":0,"pop_max":206279,"pop_min":150269,"pop_other":199844,"rank_max":10,"rank_min":9,"geonameid":2766824,"meganame":null,"ls_name":"Salzburg","ls_match":1,"checkme":0,"min_zoom":6.1,"ne_id":1159145101,"continent":"Europe"},"geometry":{"type":"Point","coordinates":[13.040020302999551,47.81047833158789]}},{"type":"Feature","properties":{"scalerank":7,"natscale":20,"labelrank":7,"featurecla":"Admin-1 capital","name":"Innsbruck","namepar":null,"namealt":null,"diffascii":0,"nameascii":"Innsbruck","adm0cap":0,"capalt":0,"capin":null,"worldcity":0,"megacity":0,"sov0name":"Austria","sov_a3":"AUT","adm0name":"Austria","adm0_a3":"AUT","adm1name":"Tirol","iso_a2":"AT","note":null,"latitude":47.2804073274,"longitude":11.4099905992,"changed":0,"namediff":0,"pop_max":155214,"pop_min":112467,"pop_other":148542,"rank_max":9,"rank_min":9,"geonameid":2775220,"meganame":null,"ls_name":"Innsbruck","ls_match":1,"checkme":0,"min_zoom":6.1,"ne_id":1159145105,"continent":"Europe"},"geometry":{"type":"Point","coordinates":[11.409990599216883,47.28040732735394]}},{"type":"Feature","properties":{"scalerank":1,"natscale":300,"labelrank":7,"featurecla":"Admin-0 capital","name":"Vienna","namepar":"Wien","namealt":null,"diffascii":0,"nameascii":"Vienna","adm0cap":1,"capalt":0,"capin":null,"worldcity":1,"megacity":1,"sov0name":"Austria","sov_a3":"AUT","adm0name":"Austria","adm0_a3":"AUT","adm1name":"Wien","iso_a2":"AT","note":null,"latitude":48.2000152782,"longitude":16.3666389554,"changed":0,"namediff":0,"pop_max":2400000,"pop_min":1731000,"pop_other":1480886,"rank_max":12,"rank_min":12,"geonameid":2761369,"meganame":"Wien","ls_name":"Vienna","ls_match":1,"checkme":0,"min_zoom":3.7,"ne_id":1159151563,"continent":"Europe"},"geometry":{"type":"Point","coordinates":[16.364693096743736,48.20196113681686]}}]}