{"type":"FeatureCollection","features":[{"type":"Feature","properties":{"scalerank":3,"natscale":110,"labelrank":0,"featurecla":"Admin-0 region capital","name":"Hamilton","namepar":null,"namealt":null,"diffascii":0,"nameascii":"Hamilton","adm0cap":1,"capalt":0,"capin":null,"worldcity":0,"megacity":0,"sov0name":"United Kingdom","sov_a3":"GBR","adm0name":"Bermuda","adm0_a3":"BMU","adm1name":null,"iso_a2":"BM","note":null,"latitude":32.2941902863,"longitude":-64.7839374203,"changed":0,"namediff":0,"pop_max":52320,"pop_min":13500,"pop_other":52320,"rank_max":8,"rank_min":6,"geonameid":3573197,"meganame":null,"ls_name":"Hamilton1","ls_match":1,"checkme":5,"min_zoom":5,"ne_id":1159151185,"continent":"North America"},"geometry":{"type":"Point","coordinates":[-64.78393742029346,32.29419028627848]}}]}